redjcaptcha/__init__.py
redjcaptcha/apps.py
redjcaptcha/models.py
redjcaptcha/redjlog.py
redjcaptcha/setup.py
redjcaptcha/urls.py
redjcaptcha/views.py
redjcaptcha/management/__init__.py
redjcaptcha/management/helper.py
redjcaptcha/management/setting.py
redjcaptcha/management/fonts/Lato-Bold.ttf
redjcaptcha/management/fonts/__init__.py
redjcaptcha/migrations/0001_initial.py
redjcaptcha/migrations/__init__.py
Redj_Captcha-1.1.8.dist-info/LICENSE
Redj_Captcha-1.1.8.dist-info/METADATA
Redj_Captcha-1.1.8.dist-info/WHEEL
Redj_Captcha-1.1.8.dist-info/top_level.txt
Redj_Captcha-1.1.8.dist-info/RECORD
